unieai_mcp_word/__init__.py
unieai_mcp_word/server.py
unieai_mcp_word-0.1.54.dist-info/licenses/LICENSE
unieai_mcp_word-0.1.54.dist-info/METADATA
unieai_mcp_word-0.1.54.dist-info/WHEEL
unieai_mcp_word-0.1.54.dist-info/entry_points.txt
unieai_mcp_word-0.1.54.dist-info/top_level.txt
unieai_mcp_word-0.1.54.dist-info/RECORD
