Metadata-Version: 2.4
Name: unieai_mcp_word
Version: 0.1.54
Summary: Internal tool for UnieAI
Home-page: https://www.unieai.com/
Author: UnieAI
Author-email: contact@unieai.com
License: Proprietary
Classifier: Programming Language :: Python :: 3
Classifier: License :: Other/Proprietary License
Classifier: Operating System :: OS Independent
Requires-Python: >=3.8
License-File: LICENSE
Requires-Dist: python-docx>=0.8.11
Requires-Dist: fastmcp>=0.1.0
Requires-Dist: httpx>=0.24.0
Dynamic: license-file
